{
  "main": {
    "id": "6f08cb08004daa11",
    "type": "split",
    "children": [
      {
        "id": "e01074a63e55db6b",
        "type": "tabs",
        "children": [
          {
            "id": "20a7964bd3636fdd",
            "type": "leaf",
            "state": {
              "type": "markdown",
              "state": {
                "file": "Photography/Portrait/From Korean MV Todays_Mod.md",
                "mode": "source",
                "source": false
              }
            }
          }
        ]
      },
      {
        "id": "1122d7e9271d5375",
        "type": "tabs",
        "children": [
          {
            "id": "6e7ca91906dca40d",
            "type": "leaf",
            "state": {
              "type": "markdown",
              "state": {
                "file": "Photography/Portrait.md",
                "mode": "source",
                "source": false
              }
            }
          }
        ]
      }
    ],
    "direction": "vertical"
  },
  "left": {
    "id": "63f1f2c62d7ce0db",
    "type": "split",
    "children": [
      {
        "id": "98bd38b3e5623e5b",
        "type": "tabs",
        "children": [
          {
            "id": "7be5dde64a5e15fa",
            "type": "leaf",
            "state": {
              "type": "file-explorer",
              "state": {
                "sortOrder": "alphabetical"
              }
            }
          },
          {
            "id": "d569f3d89ae2387f",
            "type": "leaf",
            "state": {
              "type": "search",
              "state": {
                "query": "",
                "matchingCase": false,
                "explainSearch": false,
                "collapseAll": false,
                "extraContext": false,
                "sortOrder": "alphabetical"
              }
            }
          },
          {
            "id": "0107dbf433d70cef",
            "type": "leaf",
            "state": {
              "type": "starred",
              "state": {}
            }
          }
        ]
      }
    ],
    "direction": "horizontal",
    "width": 300
  },
  "right": {
    "id": "7568d6442056d625",
    "type": "split",
    "children": [
      {
        "id": "a2c6ef5ccc9fbae4",
        "type": "tabs",
        "children": [
          {
            "id": "255ac4d336e89cdc",
            "type": "leaf",
            "state": {
              "type": "backlink",
              "state": {
                "file": "Photography/Portrait/From Korean MV Todays_Mod.md",
                "collapseAll": false,
                "extraContext": false,
                "sortOrder": "alphabetical",
                "showSearch": false,
                "searchQuery": "",
                "backlinkCollapsed": false,
                "unlinkedCollapsed": true
              }
            }
          },
          {
            "id": "a9db64571009e5ad",
            "type": "leaf",
            "state": {
              "type": "outgoing-link",
              "state": {
                "file": "Photography/Portrait/From Korean MV Todays_Mod.md",
                "linksCollapsed": false,
                "unlinkedCollapsed": true
              }
            }
          },
          {
            "id": "bbeed7e8fac972bf",
            "type": "leaf",
            "state": {
              "type": "tag",
              "state": {
                "sortOrder": "frequency",
                "useHierarchy": true
              }
            }
          },
          {
            "id": "a0da16f8c1401580",
            "type": "leaf",
            "state": {
              "type": "outline",
              "state": {
                "file": "Photography/Portrait/From Korean MV Todays_Mod.md"
              }
            }
          },
          {
            "id": "0ae214eb56fcd057",
            "type": "leaf",
            "state": {
              "type": "side-panel-control-view",
              "state": {}
            }
          }
        ],
        "currentTab": 4
      }
    ],
    "direction": "horizontal",
    "width": 300
  },
  "left-ribbon": {
    "hiddenItems": {
      "workspaces:Manage workspace layouts": false,
      "switcher:Open quick switcher": false,
      "graph:Open graph view": false,
      "canvas:Create new canvas": false,
      "templates:Insert template": false,
      "command-palette:Open command palette": false,
      "audio-recorder:Start/stop recording": false,
      "obsidian-markdown-formatting-assistant-plugin:Open Markdown Formatting Assistant": false
    }
  },
  "active": "20a7964bd3636fdd",
  "lastOpenFiles": [
    "Photography/Portrait/attachments/photo_6127648898429335195_y.jpg",
    "Photography/Portrait/attachments/photo_6127648898429335194_y.jpg",
    "Photography/Portrait/attachments/photo_6127648898429335193_y.jpg",
    "Photography/Portrait/attachments/photo_6127648898429335192_y.jpg",
    "Photography/Portrait/attachments/photo_6127648898429335191_y.jpg",
    "Photography/Portrait/attachments/photo_6127648898429335190_y.jpg",
    "Photography/Portrait/attachments/photo_6127648898429335189_y.jpg",
    "Photography/Portrait/attachments/photo_6127648898429335188_y.jpg",
    "Photography/Portrait.md",
    "Photography/Portrait/From Korean MV Todays_Mod.md",
    "Photography/Portrait/Flower_and_Girl.md",
    "文学/Love about.md",
    "Photography/Portrait/Untitled",
    "Photography/Photography_MOC.md",
    "文学/Motivation.md",
    "文学/Feeling.md",
    "文学/句子.md",
    "文学/Poem.md",
    "Photography/Saturation.md",
    "Signal Processing/Signal Processing_MOC.md",
    "Signal Processing/Basic Concepts in Signal Processing.md",
    "Signal Processing/What is dB.md",
    "Synthetic Aperture Radar Imaging/Radiometric Calibration.md",
    "Synthetic Aperture Radar Imaging/SAR Explained.md",
    "文学/Poem_by_me.md",
    "Templates/Untitled.md",
    "Templates",
    "_index.md",
    "Photography/Portrait/attachments/content.jpg",
    "Photography/Portrait/attachments/content (12).jpg",
    "Photography/Portrait/attachments/content (11).jpg",
    "Photography/Portrait/attachments",
    "Photography/Portrait",
    "Synthetic Aperture Radar Imaging/SAR_MOC.md",
    "文学/文学_MOC.md",
    "Deep Learning And Machine Learning/Deep Learning Block/⭐Attention.md",
    "Deep Learning And Machine Learning/Deep Learning Block/Transformer.md",
    "Deep Learning And Machine Learning/Deep Learning Block/Deep Learning Block.md",
    "文学/attachments",
    "Photography",
    "文学",
    "attachments/Pasted image 20230320150424.png.md",
    "Signal Processing",
    "attachments",
    "Synthetic Aperture Radar Imaging/attachments",
    "UWB/UWB Basic Information.md",
    "Untitled.canvas"
  ]
}